{
  "id": "google-scholar-policy-selection-and-schedules-for-exclusive-bus-lane-and-high-o-2025-825dbc3b",
  "author": "J Lu, Q Guo, P Schonfeld",
  "title": "Policy Selection and Schedules for Exclusive Bus Lane and High Occupancy Vehicle Lane in a Bi-modal Transportation Corridor",
  "journal": "arXiv e-prints, arXiv: 2502.08729",
  "catalog": "2025",
  "doi": "",
  "memberIds": [
    "qianwen-guo"
  ],
  "source": "google-scholar",
  "generatedAt": "2026-04-18T23:46:13.125Z",
  "lookbackYears": 2,
  "windowStartDate": "2024-04-18",
  "windowEndDate": "2026-04-18"
}
